{
  "name" : "TUserCar",
  "originTableName" : "t_user_car",
  "comment" : null,
  "fullColumn" : [ {
    "name" : "id",
    "comment" : null,
    "type" : null,
    "shortType" : null,
    "ktShortType" : "Long",
    "custom" : false,
    "ext" : { }
  }, {
    "name" : "userId",
    "comment" : null,
    "type" : null,
    "shortType" : null,
    "ktShortType" : "Long",
    "custom" : false,
    "ext" : { }
  }, {
    "name" : "carId",
    "comment" : null,
    "type" : null,
    "shortType" : null,
    "ktShortType" : "Long",
    "custom" : false,
    "ext" : { }
  }, {
    "name" : "areaCodeOriginal",
    "comment" : null,
    "type" : null,
    "shortType" : null,
    "ktShortType" : "String",
    "custom" : false,
    "ext" : { }
  }, {
    "name" : "areaCodeDestination",
    "comment" : null,
    "type" : null,
    "shortType" : null,
    "ktShortType" : "String",
    "custom" : false,
    "ext" : { }
  }, {
    "name" : "data",
    "comment" : null,
    "type" : null,
    "shortType" : null,
    "ktShortType" : "Date",
    "custom" : false,
    "ext" : { }
  }, {
    "name" : "passArea",
    "comment" : null,
    "type" : null,
    "shortType" : null,
    "ktShortType" : "String",
    "custom" : false,
    "ext" : { }
  }, {
    "name" : "paymentMethod",
    "comment" : null,
    "type" : null,
    "shortType" : null,
    "ktShortType" : "Int",
    "custom" : false,
    "ext" : { }
  }, {
    "name" : "service",
    "comment" : null,
    "type" : null,
    "shortType" : null,
    "ktShortType" : "Int",
    "custom" : false,
    "ext" : { }
  }, {
    "name" : "status",
    "comment" : null,
    "type" : null,
    "shortType" : null,
    "ktShortType" : "Int",
    "custom" : false,
    "ext" : { }
  }, {
    "name" : "goBack",
    "comment" : null,
    "type" : null,
    "shortType" : null,
    "ktShortType" : "Int",
    "custom" : false,
    "ext" : { }
  }, {
    "name" : "type",
    "comment" : null,
    "type" : null,
    "shortType" : null,
    "ktShortType" : "Int",
    "custom" : false,
    "ext" : { }
  }, {
    "name" : "price",
    "comment" : null,
    "type" : null,
    "shortType" : null,
    "ktShortType" : "Object",
    "custom" : false,
    "ext" : { }
  }, {
    "name" : "priceWay",
    "comment" : null,
    "type" : null,
    "shortType" : null,
    "ktShortType" : "Int",
    "custom" : false,
    "ext" : { }
  }, {
    "name" : "isDelete",
    "comment" : null,
    "type" : null,
    "shortType" : null,
    "ktShortType" : "Int",
    "custom" : false,
    "ext" : { }
  } ],
  "pkColumn" : null,
  "otherColumn" : null,
  "savePackageName" : "mapper",
  "savePath" : "./src/main/resources/mapper",
  "saveModelName" : "LogisticsServiceSystem"
}